{
    //Rubios
    {"r": 0.522, "g": 0.51, "b": 0.384, "a": 1, "name": "Rubio ceniza"},
    {"r": 0.494, "g": 0.478, "b": 0.333, "a": 1, "name": "Rubio claro"},
    {"r": 0.541, "g": 0.525, "b": 0.325, "a": 1, "name": "Rubio estandar"},
    {"r": 0.408, "g": 0.392, "b": 0.255, "a": 1, "name": "Rubio opaco"},
    {"r": 0.275, "g": 0.267, "b": 0.169, "a": 1, "name": "Rubio Oscuro"},

    //Anaranjados
    {"r": 0.475, "g": 0.388, "b": 0.286, "a": 1, "name": "Anaranjado ceniza"},
    {"r": 0.435, "g": 0.345, "b": 0.231, "a": 1, "name": "Anaranjado claro"},
    {"r": 0.475, "g": 0.353, "b": 0.2, "a": 1, "name": "Anaranjado estandar"},
    {"r": 0.388, "g": 0.278, "b": 0.141, "a": 1, "name": "Anaranjado opaco"},
    {"r": 0.353, "g": 0.227, "b": 0.075, "a": 1, "name": "Anaranjado Oscuro"},

    //Pelirojos
    {"r": 0.447, "g": 0.282, "b": 0.243, "a": 1, "name": "Pelirojo ceniza"},
    {"r": 0.408, "g": 0.239, "b": 0.2, "a": 1, "name": "Pelirojo claro"},
    {"r": 0.333, "g": 0.165, "b": 0.129, "a": 1, "name": "Pelirojo estandar"},
    {"r": 0.294, "g": 0.173, "b": 0.145, "a": 1, "name": "Pelirojo opaco"},
    {"r": 0.239, "g": 0.133, "b": 0.11, "a": 1, "name": "Pelirojo Oscuro"},

    //Castaños
    {"r": 0.239, "g": 0.216, "b": 0.2, "a": 1, "name": "Castaño ceniza"},
    {"r": 0.247, "g": 0.208, "b": 0.169, "a": 1, "name": "Castaño claro"},
    {"r": 0.255, "g": 0.2, "b": 0.145, "a": 1, "name": "Castaño estandar"},
    {"r": 0.173, "g": 0.141, "b": 0.11, "a": 1, "name": "Castaño opaco"},
    {"r": 0.114, "g": 0.098, "b": 0.078, "a": 1, "name": "Castaño Oscuro"},

    //Oscuros
    {"r": 0.569, "g": 0.569, "b": 0.569, "a": 1, "name": "Gris ceniza"},
    {"r": 0.388, "g": 0.380, "b": 0.376, "a": 1, "name": "Gris claro"},
    {"r": 0.247, "g": 0.247, "b": 0.247, "a": 1, "name": "Gris estandar"},
    {"r": 0.18, "g": 0.18, "b": 0.18, "a": 1, "name": "Negro estandar"},
    {"r": 0.086, "g": 0.086, "b": 0.086, "a": 1, "name": "Negro Oscuro"}
}